{
  "name": "PessoaMedico",
  "fields": [
    {
      "fieldName": "id",
      "fieldType": "Long"
    },
    {
      "fieldName": "crm",
      "fieldType": "String",
      "fieldValidateRules": ["required", "unique"]
    }
  ],
  "relationships": [
    {
      "relationshipType": "one-to-many",
      "otherEntityName": "pessoa",
      "otherEntityRelationshipName": "pessoaMedico",
      "relationshipName": "pessoa"
    }
  ],
  "entityTableName": "pessoa_medico",
  "dto": "no",
  "pagination": "no",
  "service": "no",
  "jpaMetamodelFiltering": false,
  "fluentMethods": true,
  "readOnly": false,
  "embedded": false,
  "applications": ["core"],
  "microserviceName": "core",
  "clientRootFolder": "core",
  "databaseType": "sql",
  "changelogDate": "20210910141003"
}
